etb_db/DB.py
etb_db/__init__.py
etb_db-0.1.9.dist-info/LICENSE
etb_db-0.1.9.dist-info/METADATA
etb_db-0.1.9.dist-info/WHEEL
etb_db-0.1.9.dist-info/RECORD
